FamcyTools/__init__.py
FamcyTools/main.py
FamcyTools/scripts/deploy.py
FamcyTools/scripts/env_init.py
FamcyTools/scripts/famcy_upgrade.py
FamcyTools/scripts/start.py
FamcyTools/scripts/bash/init.sh
FamcyTools/scripts/bash/run.sh
FamcyTools/scripts/bash/upgrade.sh
FamcyTools-0.0.33.dist-info/LICENSE
FamcyTools-0.0.33.dist-info/METADATA
FamcyTools-0.0.33.dist-info/WHEEL
FamcyTools-0.0.33.dist-info/entry_points.txt
FamcyTools-0.0.33.dist-info/top_level.txt
FamcyTools-0.0.33.dist-info/RECORD
