Metadata-Version: 2.1
Name: FamcyTools
Version: 0.0.33
Summary: Nexuni Co Ltd. Famcy management console framework
Home-page: https://github.com/nexuni/FamcyTools.git
Author: Nexuni Co Ltd. Develop Team
Author-email: developers@nexuni.com
License: Apache-2.0
Platform: UNKNOWN
Classifier: Intended Audience :: Developers
Classifier: License :: OSI Approved :: Apache Software License
Classifier: Programming Language :: Python :: 3.6
Classifier: Programming Language :: Python :: 3.7
Classifier: Operating System :: OS Independent
Classifier: Topic :: Software Development :: Libraries 
Requires-Python: >=3.6
Requires-Dist: gadgethiServerUtils (==999.999)
